LICENSE
MANIFEST.in
README.rst
setup.py
django_python3_saml/__init__.py
django_python3_saml/admin.py
django_python3_saml/backends.py
django_python3_saml/example_settings.py
django_python3_saml/models.py
django_python3_saml/saml_settings.py
django_python3_saml/tests.py
django_python3_saml/urls.py
django_python3_saml/utils.py
django_python3_saml/views.py
django_python3_saml.egg-info/PKG-INFO
django_python3_saml.egg-info/SOURCES.txt
django_python3_saml.egg-info/dependency_links.txt
django_python3_saml.egg-info/requires.txt
django_python3_saml.egg-info/top_level.txt
django_python3_saml/migrations/__init__.py