Metadata-Version: 1.1
Name: django-python3-saml
Version: 1.0
Summary: Django SAML auth plugin for python 3
Home-page: https://github.com/IronCountySchoolDistrict/django-python3-saml
Author: Issac Gable
Author-email: issac.gable@ironmail.org
License: BSD 3-Clause License
Platform: UNKNOWN
Classifier: Environment :: Web Environment
Classifier: Framework :: Django
Classifier: Framework :: Django :: 1.11
Classifier: Intended Audience :: Developers
Classifier: License :: OSI Approved :: BSD License
Classifier: Operating System :: OS Independent
Classifier: Programming Language :: Python
Classifier: Programming Language :: Python :: 3
Classifier: Programming Language :: Python :: 3.4
Classifier: Programming Language :: Python :: 3.5
Classifier: Topic :: Internet :: WWW/HTTP
Classifier: Topic :: Internet :: WWW/HTTP :: Dynamic Content
Classifier: Development Status :: 4 - Beta
